setup.py
openvas_tasks/__init__.py
openvas_tasks/ovastypes.py
openvas_tasks/tasks.py
openvas_tasks.egg-info/PKG-INFO
openvas_tasks.egg-info/SOURCES.txt
openvas_tasks.egg-info/dependency_links.txt
openvas_tasks.egg-info/not-zip-safe
openvas_tasks.egg-info/requires.txt
openvas_tasks.egg-info/top_level.txt