Metadata-Version: 1.1
Name: openvas-tasks
Version: 1.0
Summary: Information and history receptor for OpenVAS tasks
Home-page: http://vertexclique.github.io/openvas_tasks
Author: Mahmut Bulut (vertexclique)
Author-email: mahmut@mahmutbulut.com
License: MIT
Download-URL: https://github.com/vertexclique/openvas_tasks/zipball/master
Platform: UNKNOWN
Classifier: Development Status :: 4 - Beta
Classifier: Intended Audience :: Developers
Classifier: Intended Audience :: Information Technology
Classifier: License :: OSI Approved :: MIT License
Classifier: Natural Language :: English
Classifier: Operating System :: MacOS :: MacOS X
Classifier: Operating System :: Microsoft :: Windows
Classifier: Operating System :: POSIX
Classifier: Operating System :: POSIX :: BSD :: FreeBSD
Classifier: Operating System :: POSIX :: Linux
Classifier: Operating System :: Unix
Classifier: Programming Language :: Python :: 2.7
Classifier: Topic :: Security
Provides: openvas_tasks
